horace/__init__.py
horace/horace.py
horace-0.1.0.dist-info/AUTHORS.rst
horace-0.1.0.dist-info/LICENSE
horace-0.1.0.dist-info/LICENSE.old
horace-0.1.0.dist-info/METADATA
horace-0.1.0.dist-info/WHEEL
horace-0.1.0.dist-info/top_level.txt
horace-0.1.0.dist-info/RECORD
