Metadata-Version: 2.1
Name: horace
Version: 0.1.0
Summary: Format converter from PoetryLab JSON to POSTDATA semantic formats
Home-page: https://github.com/linhd-postdata/horace
Author: LINHD POSTDATA Project
Author-email: info@linhd.uned.es
License: Apache Software License 2.0
Keywords: horace
Platform: UNKNOWN
Classifier: Development Status :: 2 - Pre-Alpha
Classifier: Intended Audience :: Developers
Classifier: License :: OSI Approved :: Apache Software License
Classifier: Natural Language :: English
Classifier: Programming Language :: Python :: 3
Classifier: Programming Language :: Python :: 3.5
Classifier: Programming Language :: Python :: 3.6
Classifier: Programming Language :: Python :: 3.7
Classifier: Programming Language :: Python :: 3.8
Requires-Python: >=3.5
